zahlwort2num/__init__.py
zahlwort2num/__version__.py
zahlwort2num/command_line.py
zahlwort2num/tests/__init__.py
zahlwort2num/tests/test_console.py
zahlwort2num/tests/test_convert.py
zahlwort2num-1.0.1.data/scripts/zahlwort2num-convert
zahlwort2num-1.0.1.dist-info/licenses/LICENSE
zahlwort2num-1.0.1.dist-info/METADATA
zahlwort2num-1.0.1.dist-info/WHEEL
zahlwort2num-1.0.1.dist-info/entry_points.txt
zahlwort2num-1.0.1.dist-info/top_level.txt
zahlwort2num-1.0.1.dist-info/RECORD
