Metadata-Version: 2.4
Name: zahlwort2num
Version: 1.0.1
Summary: A small package for handy conversion of german numerals (also ordinal / signed) written as words to numbers.
Home-page: https://github.com/walu2/zahlwort2num
Author: Piotr Walkowski
Author-email: piotr@deluxe-soft.com
Keywords: german nlp numeral converter deutsch sprache ordinal zahlen human number
Classifier: Programming Language :: Python :: 3
Classifier: License :: OSI Approved :: MIT License
Classifier: Operating System :: OS Independent
Classifier: Topic :: Text Processing :: Linguistic
License-File: LICENSE
Requires-Dist: markdown
Dynamic: author
Dynamic: author-email
Dynamic: classifier
Dynamic: description
Dynamic: description-content-type
Dynamic: home-page
Dynamic: keywords
Dynamic: license-file
Dynamic: requires-dist
Dynamic: summary
